{
    "intro":  [
    	"michael sjoeberg"
    ],
    "recent": {
    	"20201104": {
    		"title": "Genetic Algorithm Optimization in Python",
    		"url": "/programming/python/other/genetic-algorithm-optimization"
    	},
    	"20201102": {
    		"title": "Basics and Other in C++",
    		"url": "/programming#c++"
    	},
        "20201024": {
            "title": "Special Pythagorean Triplet in Python",
            "url": "/programming/python/project-euler-problems/special-pythagorean-triplet"
        }
    }
}
